dcdf/__init__.py
dcdf/cli.py
dcdf/data.py
dcdf/measure.py
dcdf/parallel-shared_memory.py
dcdf/parallel.py
dcdf-0.1.8.dist-info/LICENSE
dcdf-0.1.8.dist-info/METADATA
dcdf-0.1.8.dist-info/WHEEL
dcdf-0.1.8.dist-info/entry_points.txt
dcdf-0.1.8.dist-info/top_level.txt
dcdf-0.1.8.dist-info/RECORD
