Metadata-Version: 2.1
Name: dcdf
Version: 0.1.8
Summary: Package to compute DCDF for nifti formatted MRI data.
Home-page: https://github.com/ForrestCKoch/DCDF
Author: Forrest Koch
Author-email: forrest.koch@unsw.edu.au
Maintainer: Forrest Koch
Maintainer-email: forrest.koch@unsw.edu.au
License: UNKNOWN
Keywords: MRI nifti dti neuroimaging dcdf
Platform: UNKNOWN
Requires-Dist: numpy
Requires-Dist: nibabel
Requires-Dist: pandas
Requires-Dist: scipy
Requires-Dist: sphinx
Requires-Dist: sphinx-rtd-theme
